{
  "author": "Rachel Wetzsteon",
  "classification": "",
  "keywords": [],
  "period": "",
  "reference": "http://www.poetryfoundation.org/poetrymagazine/poem/240206",
  "region": "",
  "text": [
    "I\u2019ll fly off to a fjord in Norway,",
    "post \u201cOh the pain\u201d above my doorway",
    "if you insist on going your way,",
    "for this is not a duck.",
    "That is what cowards say, and realists",
    "who run away, shun the appeal its",
    "rare white fur holds, although they feel it\u2019s",
    "a rabbit full of pluck.",
    "Let\u2019s multiply, let\u2019s twitch our noses,",
    "let\u2019s walk among the night\u2019s dark roses,",
    "though where the oldest story goes is",
    "a place where tongues might cluck.",
    "I\u2019ve had my share of quacks and hisses;",
    "whereof mouth cannot speak, it kisses;",
    "hop to it, man, and realize this is",
    "a lovely bit of luck."
  ],
  "title": "Cabaret Ludwig",
  "year": ""
}