{
  "author": "Atsuro Riley",
  "classification": "",
  "keywords": [],
  "period": "",
  "reference": "http://www.poetryfoundation.org/poetrymagazine/poem/182107",
  "region": "",
  "text": [
    "Her cart like a dugout canoe.",
    "Had been an oak trunk.",
    "Cut young. Fire-scoured.",
    "What was bark what was heartwood :",
    "Adze-hacked and gouged.",
    "Ever after (never not) wheeling hollow there behind her.",
    "Up the hill toward Bennett Yard; down through Eight-Mile,",
    "the Narrows.",
    "Body bent past bent. Intent upon horizon and carry.",
    "Her null eye long since gone isinglassy, opal.",
    "\u2014The potent (brimming, fluent) one looks brown.",
    "Bearing (and borne ahead by) hull and hold behind her.",
    "Plies the dark.",
    "Whole nights most nights along the overpass over Accabee.",
    "Pausing and voweling there\u2014 the place where the girl fell.",
    "( )",
    "Afterwhile passing.",
    "Comes her cart like a whole-note held."
  ],
  "title": "Clary",
  "year": ""
}