{
  "author": "John Yau",
  "classification": "",
  "keywords": [
    "Arts",
    "Sciences",
    "Language",
    "Linguistics",
    "Social Commentaries",
    "Money",
    "Economics",
    "Popular Culture"
  ],
  "period": "",
  "reference": "http://www.poetryfoundation.org/poem/246654",
  "region": "",
  "text": [
    "I used to be a plastic bottle",
    "I used to be scads of masticated wattle",
    "I used to be epic spittle, aka septic piddle",
    "I used to be a pleasant colleague",
    "I used to be a radiant ingredient",
    "I used to be a purple polyethylene pony",
    "I used to be a phony upload project",
    "I used to be a stony blue inhalant",
    "I used to be a family-size turquoise bottle",
    "I used to be a domesticated pink bubble",
    "I used to be a pleasant red colleague",
    "I used to be a beaming cobalt emollient",
    "I used to be a convenient chartreuse antidepressant"
  ],
  "title": "Confessions of a Recycled Shopping Bag",
  "year": ""
}