{
  "author": "Terese Svoboda",
  "classification": "",
  "keywords": [],
  "period": "",
  "reference": "http://www.poetryfoundation.org/poetrymagazine/poem/250096",
  "region": "",
  "text": [
    "You could hike over it, the you",
    "without a problem, its mountain",
    "viewed from the closet",
    "coats are found in, your constant",
    "Yes/No a hee-haw, a mule alert",
    "that\u2019s pasture-perfect,",
    "a coronary at the last corner.",
    "Nobody\u2019s framing you for the chintz-",
    "covered wall to cover the leak.",
    "Besides, you like leaks, you\u2019re inside",
    "the view as if hibernating",
    "or crazy, you try not to erupt.",
    "Hypothesize the rest,",
    "the languor and freshet,",
    "the crags, the serrated parade.",
    "So \u2014 heights? What about the hairy stream,",
    "the pushed-up bushes saying",
    "?",
    "You got a problem with that?",
    "is what you call it",
    "a voice off the hanger, the blouse",
    "cast in a corner or animate."
  ],
  "title": "Hairy Stream",
  "year": ""
}