{
  "author": "Julie Suk",
  "classification": "",
  "keywords": [],
  "period": "",
  "reference": "http://www.poetryfoundation.org/poem/244030",
  "region": "U.S., Southern",
  "text": [
    "I could make a wardrobe",
    "with tufts of wool",
    "caught on thistle and bracken.",
    "Lost\u2014the scraps",
    "I might have woven whole cloth.",
    "the man says,",
    "shearing sheep",
    "with the precision of long practice,",
    "fleece, removed all of a piece,",
    "rolled in a neat bundle.",
    "I\u2019ve been so clumsy",
    "with people who\u2019ve loved me.",
    "Straddling a ewe,",
    "the man props its head on his foot,",
    "leans down with clippers,",
    "each pass across the coat a caress.",
    "His dogs, lying nearby,",
    "tremble at every move\u2014as I do,",
    "loving the hands that have learned",
    "to gentle the life beneath them."
  ],
  "title": "Loving the Hands",
  "year": ""
}